erp_apis_temp/config.py
erp_apis_temp/erpRequest.py
erp_apis_temp/apis/afterSales.py
erp_apis_temp/apis/goods.py
erp_apis_temp/apis/inventory.py
erp_apis_temp/apis/order.py
erp_apis_temp/apis/print.py
erp_apis_temp/apis/refund.py
erp_apis_temp/apis/user.py
erp_apis_temp/utils/util.py
erp_apis_temp-1.0.33.dist-info/METADATA
erp_apis_temp-1.0.33.dist-info/WHEEL
erp_apis_temp-1.0.33.dist-info/top_level.txt
erp_apis_temp-1.0.33.dist-info/RECORD
