Metadata-Version: 2.1
Name: erp_apis_temp
Version: 1.0.33
Summary: erp_apis_temp
Author: 李福成
Author-email: lfct@qq.com
License: MIT
Project-URL: Bug Tracker, https://gitee.com/li_fucheng/erp_sdk_python/issues
Project-URL: Documentation, https://gitee.com/li_fucheng/erp_sdk_python
Project-URL: Source Code, https://gitee.com/li_fucheng/erp_sdk_python
Keywords: erp_apis_temp
Classifier: Development Status :: 5 - Production/Stable
Classifier: Intended Audience :: Developers
Classifier: Topic :: Software Development :: Build Tools
Classifier: License :: OSI Approved :: MIT License
Classifier: Programming Language :: Python :: 3
Classifier: Programming Language :: Python :: 3.6
Classifier: Programming Language :: Python :: 3.7
Classifier: Programming Language :: Python :: 3.8
Classifier: Programming Language :: Python :: 3.9
Classifier: Programming Language :: Python :: 3.10
Requires-Dist: requests
Requires-Dist: lxml
